shamrock/__init__.py
shamrock/decorators.py
shamrock/exceptions.py
shamrock/messages.py
shamrock/shamrock.py
shamrock-0.2.0.dist-info/AUTHORS.rst
shamrock-0.2.0.dist-info/LICENSE
shamrock-0.2.0.dist-info/METADATA
shamrock-0.2.0.dist-info/WHEEL
shamrock-0.2.0.dist-info/top_level.txt
shamrock-0.2.0.dist-info/RECORD
