Metadata-Version: 2.1
Name: shamrock
Version: 0.2.0
Summary: A Trefle API Integration.
Home-page: https://github.com/zmasek/shamrock
Author: Zlatko Mašek
Author-email: zlatko.masek@gmail.com
License: MIT license': 'License :: OSI Approved :: MIT License
Keywords: shamrock
Platform: UNKNOWN
Classifier: Development Status :: 2 - Pre-Alpha
Classifier: Intended Audience :: Developers
Classifier: License :: OSI Approved :: MIT License
Classifier: Natural Language :: English
Classifier: Programming Language :: Python :: 3.6
Classifier: Programming Language :: Python :: 3.7
Requires-Dist: requests (==2.21.0)
